Workbook
Name aporte: Simulador_FII!$E$22
Name patrimonio: Simulador_FII!$E$25
Name qtd_anos: Simulador_FII!$E$23
Name rendimento_carteira: Simulador_FII!$E$18
Name salario: Simulador_FII!$E$17
Name sugestao_investimento: Simulador_FII!$E$19
Name taxa_mensal: Simulador_FII!$E$24

Sheet Simulador_FII
B13: SIMULADOR DE INVESTIMENTO EM FIIs
B14: Planejamento Financeiro, Acúmulo de Patrimônio e Distribuição por Perfil
B16: 1. CONFIGURAÇÕES BASE
B17: Salário Mensal (R$) | E17: 5000
B18: Rendimento Estimado da Carteira (% a.m.) | E18: 0.006
B19: Sugestão de Aporte (30% do Salário) | E19: =salario*0.3 -> 1500
B21: 2. PERGUNTAS DE NEGÓCIO (SIMULAÇÃO MENSAL)
B22: 1. Quanto investir por mês? | E22: 500
B23: 2. Por quantos anos? | E23: 5
B24: 3. Qual a taxa de rendimento mensal? | E24: 0.01079
B25: 4. Quanto de patrimônio vai acumular? | E25: =-FV(taxa_mensal, qtd_anos*12, aporte) -> 41888.457
B26: 5. Quanto vai receber de dividendos por mês? | E26: =patrimonio*rendimento_carteira -> 251.33074
B27: *Dividendos (30% Salário - Aporte Sugerido) | E27: =-FV(taxa_mensal, qtd_anos*12, sugestao_investimento)*rendimento_carteira -> 753.99223
B29: 3. PROJEÇÃO DE CENÁRIOS (2 A 30 ANOS)
B30: Prazo (Anos) | C30: Patrimônio Acumulado (Aporte Informado) | D30: Dividendo Mensal (Aporte Informado) | E30: Patrimônio (Aporte 30%) | F30: Dividendo (Aporte 30%)
B31: 2 anos | C31: =-FV(taxa_mensal, 2*12, aporte) -> 13613.814 | D31: =C31*rendimento_carteira -> 81.682882 | E31: =-FV(taxa_mensal, 2*12, sugestao_investimento) -> 40841.441 | F31: =E31*rendimento_carteira -> 245.04865
B32: 5 anos | C32: =-FV(taxa_mensal, 5*12, aporte) -> 41888.457 | D32: =C32*rendimento_carteira -> 251.33074 | E32: =-FV(taxa_mensal, 5*12, sugestao_investimento) -> 125665.37 | F32: =E32*rendimento_carteira -> 753.99223
B33: 10 anos | C33: =-FV(taxa_mensal, 10*12, aporte) -> 121642.11 | D33: =C33*rendimento_carteira -> 729.85264 | E33: =-FV(taxa_mensal, 10*12, sugestao_investimento) -> 364926.32 | F33: =E33*rendimento_carteira -> 2189.5579
B34: 20 anos | C34: =-FV(taxa_mensal, 20*12, aporte) -> 562599.2 | D34: =C34*rendimento_carteira -> 3375.5952 | E34: =-FV(taxa_mensal, 20*12, sugestao_investimento) -> 1687797.6 | F34: =E34*rendimento_carteira -> 10126.786
B35: 30 anos | C35: =-FV(taxa_mensal, 30*12, aporte) -> 2161084.8 | D35: =C35*rendimento_carteira -> 12966.509 | E35: =-FV(taxa_mensal, 30*12, sugestao_investimento) -> 6483254.5 | F35: =E35*rendimento_carteira -> 38899.527
B38: 4. ALOCAÇÃO DO APORTE POR PERFIL DE INVESTIDOR
B39: Perfil Selecionado: | C39: AGRESSIVO
B40: Valor a ser Investido Mensal: | C40: 800
B41: Tipo de FII | C41: Percentual Sugerido | D41: Valor Alocado (R$)
B42: PAPEL | C42: =VLOOKUP($C$39&"-"&B42, Chaves!$A:$D, 4, FALSE) -> 0.5 | D42: =$C$40*C42 -> 400
B43: TIJOLO | C43: =VLOOKUP($C$39&"-"&B43, Chaves!$A:$D, 4, FALSE) -> 0.1 | D43: =$C$40*C43 -> 80
B44: HIBRIDOS | C44: =VLOOKUP($C$39&"-"&B44, Chaves!$A:$D, 4, FALSE) -> 0.05 | D44: =$C$40*C44 -> 40
B45: FOFS | C45: =VLOOKUP($C$39&"-"&B45, Chaves!$A:$D, 4, FALSE) -> 0.05 | D45: =$C$40*C45 -> 40
B46: DESENVOLVIMENTO | C46: =VLOOKUP($C$39&"-"&B46, Chaves!$A:$D, 4, FALSE) -> 0.2 | D46: =$C$40*C46 -> 160
B47: HOTELARIAS | C47: =VLOOKUP($C$39&"-"&B47, Chaves!$A:$D, 4, FALSE) -> 0.1 | D47: =$C$40*C47 -> 80
B48: TOTAL | C48: =SUM(C42:C47) -> 1 | D48: =SUM(D42:D47) -> 800

Sheet Chaves
A1: CHAVE | B1: PERFIL | C1: TIPO DE FII | D1: PERCENTUAL
A2: =B2&"-"&C2 -> CONSERVADOR-PAPEL | B2: CONSERVADOR | C2: PAPEL | D2: 0.3
A3: =B3&"-"&C3 -> CONSERVADOR-TIJOLO | B3: CONSERVADOR | C3: TIJOLO | D3: 0.5
A4: =B4&"-"&C4 -> CONSERVADOR-HIBRIDOS | B4: CONSERVADOR | C4: HIBRIDOS | D4: 0.1
A5: =B5&"-"&C5 -> CONSERVADOR-FOFS | B5: CONSERVADOR | C5: FOFS | D5: 0.1
A6: =B6&"-"&C6 -> CONSERVADOR-DESENVOLVIMENTO | B6: CONSERVADOR | C6: DESENVOLVIMENTO | D6: 0
A7: =B7&"-"&C7 -> CONSERVADOR-HOTELARIAS | B7: CONSERVADOR | C7: HOTELARIAS | D7: 0
A8: =B8&"-"&C8 -> MODERADO-PAPEL | B8: MODERADO | C8: PAPEL | D8: 0.32
A9: =B9&"-"&C9 -> MODERADO-TIJOLO | B9: MODERADO | C9: TIJOLO | D9: 0.35
A10: =B10&"-"&C10 -> MODERADO-HIBRIDOS | B10: MODERADO | C10: HIBRIDOS | D10: 0.08
A11: =B11&"-"&C11 -> MODERADO-FOFS | B11: MODERADO | C11: FOFS | D11: 0.05
A12: =B12&"-"&C12 -> MODERADO-DESENVOLVIMENTO | B12: MODERADO | C12: DESENVOLVIMENTO | D12: 0.1
A13: =B13&"-"&C13 -> MODERADO-HOTELARIAS | B13: MODERADO | C13: HOTELARIAS | D13: 0.1
... A19: =B19&"-"&C19 -> AGRESSIVO-HOTELARIAS | B19: AGRESSIVO | C19: HOTELARIAS | D19: 0.1
